{
  "generated_at": "2026-07-24T06:05:12.221Z",
  "jobs": [
    {
      "n": 1,
      "title": "Product Manager",
      "company": "PlaySimple Games",
      "location": "Bengaluru, Karnataka, India",
      "url": "https://www.linkedin.com/jobs/view/4444312084"
    },
    {
      "n": 2,
      "title": "Product Manager — Travel & Hospitality Tech",
      "company": "Finkraft",
      "location": "Bangalore Urban, Karnataka, India",
      "url": "https://www.linkedin.com/jobs/view/4434974709"
    },
    {
      "n": 3,
      "title": "Product Manager",
      "company": "NxtWave",
      "location": "Hyderabad, Telangana, India",
      "url": "https://www.linkedin.com/jobs/view/4432196639"
    },
    {
      "n": 4,
      "title": "Product Manager — Virtual Cards",
      "company": "Finkraft",
      "location": "Bengaluru, Karnataka, India",
      "url": "https://www.linkedin.com/jobs/view/4443818683"
    },
    {
      "n": 5,
      "title": "Product Manager : Data Platform",
      "company": "Job-scouts.com",
      "location": "Bengaluru, Karnataka, India",
      "url": "https://www.linkedin.com/jobs/view/4444790994"
    },
    {
      "n": 6,
      "title": "Product Owner || Pharmacy Benefit Manager (PBM ) Must hv || 5+ Yrs || Pan India",
      "company": "Innova ESI",
      "location": "Bengaluru, Karnataka, India",
      "url": "https://www.linkedin.com/jobs/view/4444911248"
    },
    {
      "n": 7,
      "title": "Product Manager II",
      "company": "Zynga",
      "location": "Bengaluru, India",
      "url": "https://job-boards.greenhouse.io/zyngacareers/jobs/6112484004"
    }
  ]
}