{
  "generated_at": "2026-07-18T05:37:09.048Z",
  "jobs": [
    {
      "n": 1,
      "title": "Digital Pricing Product Owner",
      "company": "Takeda",
      "location": "Bengaluru, Karnataka, India",
      "url": "https://www.linkedin.com/jobs/view/4439286827"
    },
    {
      "n": 2,
      "title": "Digital Access Product Owner",
      "company": "Takeda",
      "location": "Bengaluru, Karnataka, India",
      "url": "https://www.linkedin.com/jobs/view/4439296520"
    },
    {
      "n": 3,
      "title": "Value and Evidence Product Owner",
      "company": "Takeda",
      "location": "Bengaluru, Karnataka, India",
      "url": "https://www.linkedin.com/jobs/view/4439284888"
    }
  ]
}