{
  "generated_at": "2026-07-20T10:20:56.502Z",
  "jobs": [
    {
      "n": 1,
      "title": "Senior Product Manager",
      "company": "Soar",
      "location": "Bengaluru, Karnataka, India",
      "url": "https://www.linkedin.com/jobs/view/4440129328"
    },
    {
      "n": 2,
      "title": "Senior Product Owner",
      "company": "Fractal",
      "location": "Gurgaon, Haryana, India",
      "url": "https://www.linkedin.com/jobs/view/4433668231"
    },
    {
      "n": 3,
      "title": "Senior Product Manager",
      "company": "IOT Solutions World",
      "location": "Pune Division, Maharashtra, India",
      "url": "https://www.linkedin.com/jobs/view/4440125511"
    },
    {
      "n": 4,
      "title": "Senior Lead Product Owner - Payment Products",
      "company": "Wells Fargo",
      "location": "Bengaluru, Karnataka, India",
      "url": "https://www.linkedin.com/jobs/view/4442596308"
    },
    {
      "n": 5,
      "title": "Chief Product Officer",
      "company": "Soar",
      "location": "Channagiri, Karnataka, India",
      "url": "https://www.linkedin.com/jobs/view/4440130257"
    },
    {
      "n": 6,
      "title": "Product Manager",
      "company": "LoansJagat",
      "location": "Noida, Uttar Pradesh, India",
      "url": "https://www.linkedin.com/jobs/view/4442701054"
    },
    {
      "n": 7,
      "title": "Technical Product Manager [T500-27206]",
      "company": "TMUS Global Solutions",
      "location": "Hyderabad, Telangana, India",
      "url": "https://www.linkedin.com/jobs/view/4442592506"
    },
    {
      "n": 8,
      "title": "Product Manager",
      "company": "Leucine - AI for Pharma",
      "location": "Bengaluru, Karnataka, India",
      "url": "https://www.linkedin.com/jobs/view/4442589612"
    },
    {
      "n": 9,
      "title": "Product Manager",
      "company": "LTIMindtree",
      "location": "Karnataka, India",
      "url": "https://www.linkedin.com/jobs/view/4440129144"
    },
    {
      "n": 10,
      "title": "Product Owner Manager",
      "company": "Revenera",
      "location": "Bengaluru, Karnataka, India",
      "url": "https://www.linkedin.com/jobs/view/4412255723"
    },
    {
      "n": 11,
      "title": "Product manager For Australia  Opportunities",
      "company": "Esse India | Canada immigration consultants in delhi | visa consultant delhi",
      "location": "Bengaluru, Karnataka, India",
      "url": "https://www.linkedin.com/jobs/view/4442023714"
    },
    {
      "n": 12,
      "title": "Product Manager, Van Heusen",
      "company": "Aditya Birla Fashion and Retail Ltd.",
      "location": "Karnataka, India",
      "url": "https://www.linkedin.com/jobs/view/4442584682"
    },
    {
      "n": 13,
      "title": "Staff Product Manager",
      "company": "Freshworks",
      "location": "Bengaluru, in",
      "url": "https://api.smartrecruiters.com/v1/companies/Freshworks/postings/744000138563850"
    },
    {
      "n": 14,
      "title": "Senior Product Manager",
      "company": "ixigo",
      "location": "New Delhi, in",
      "url": "https://api.smartrecruiters.com/v1/companies/ixigo/postings/744000138573376"
    }
  ]
}