{
  "generated_at": "2026-05-30T12:17:25.680Z",
  "jobs": [
    {
      "n": 1,
      "title": "Group Product Manager, Google Play",
      "company": "Google",
      "location": "Bengaluru, Karnataka, India",
      "url": "https://www.linkedin.com/jobs/view/4412139487"
    },
    {
      "n": 2,
      "title": "Senior Product Manager, India Global Trade",
      "company": "Amazon",
      "location": "Bengaluru, Karnataka, India",
      "url": "https://www.linkedin.com/jobs/view/4381961745"
    },
    {
      "n": 3,
      "title": "Senior Technical Product Owner",
      "company": "LPL Financial Global Capability Center",
      "location": "Greater Hyderabad Area",
      "url": "https://www.linkedin.com/jobs/view/4411378932"
    },
    {
      "n": 4,
      "title": "Product Manager",
      "company": "Sibros",
      "location": "Pune Division, Maharashtra, India",
      "url": "https://www.linkedin.com/jobs/view/4391545896"
    },
    {
      "n": 5,
      "title": "Associate Product Manager | Pune",
      "company": "Cornerstone OnDemand",
      "location": "Pune Division, Maharashtra, India",
      "url": "https://www.linkedin.com/jobs/view/4412160230"
    },
    {
      "n": 6,
      "title": "Staff Product Manager - Mobile Platform",
      "company": "HighLevel",
      "location": "India",
      "url": "https://www.linkedin.com/jobs/view/4412124593"
    },
    {
      "n": 7,
      "title": "Senior Product Manager",
      "company": "Sprinklr",
      "location": "India - Haryana - Gurgaon",
      "url": "https://sprinklr.wd1.myworkdayjobs.com/careers/job/India---Haryana---Gurgaon/Senior-Product-Manager_112721-JOB"
    }
  ]
}