{
  "generated_at": "2026-07-21T08:46:33.511Z",
  "jobs": [
    {
      "n": 1,
      "title": "Product Manager - Data Platforms",
      "company": "EPAM Systems",
      "location": "Pune Division, Maharashtra, India",
      "url": "https://www.linkedin.com/jobs/view/4440415925"
    },
    {
      "n": 2,
      "title": "Product Manager",
      "company": "Asper.ai",
      "location": "Bengaluru, Karnataka, India",
      "url": "https://www.linkedin.com/jobs/view/4442609206"
    },
    {
      "n": 3,
      "title": "Product Manager – AI Products",
      "company": "OnPoint Insights",
      "location": "Mumbai, Maharashtra, India",
      "url": "https://www.linkedin.com/jobs/view/4443312845"
    },
    {
      "n": 4,
      "title": "Product Manager - Ad Tech & Monetization",
      "company": "Mirchi",
      "location": "Noida, Uttar Pradesh, India",
      "url": "https://www.linkedin.com/jobs/view/4443337052"
    },
    {
      "n": 5,
      "title": "Product Manager",
      "company": "Marvin",
      "location": "India",
      "url": "https://www.linkedin.com/jobs/view/4443316709"
    },
    {
      "n": 6,
      "title": "Associate Product Manager",
      "company": "Phenom",
      "location": "Hyderabad, Telangana, India",
      "url": "https://www.linkedin.com/jobs/view/4443329155"
    },
    {
      "n": 7,
      "title": "Director of Product Operations",
      "company": "Arctic Wolf",
      "location": "Bengaluru, Karnataka, India",
      "url": "https://www.linkedin.com/jobs/view/4440424547"
    },
    {
      "n": 8,
      "title": "Senior Product Manager",
      "company": "Tekion Corp",
      "location": "Bengaluru, Karnataka, India",
      "url": "https://job-boards.greenhouse.io/tekion/jobs/7782738003"
    }
  ]
}