{
  "generated_at": "2026-06-13T07:07:28.712Z",
  "jobs": [
    {
      "n": 1,
      "title": "Global Ownership Product Manager",
      "company": "Innomax IT Solutions",
      "location": "Hyderabad, Telangana, India",
      "url": "https://www.linkedin.com/jobs/view/4425591814"
    },
    {
      "n": 2,
      "title": "Product Manager (Up to 60LPA)",
      "company": "CodeRound AI",
      "location": "India",
      "url": "https://www.linkedin.com/jobs/view/4425344748"
    },
    {
      "n": 3,
      "title": "Staff Product Manager",
      "company": "Twilio",
      "location": "Remote - Canada",
      "url": "https://job-boards.greenhouse.io/twilio/jobs/7904293"
    },
    {
      "n": 4,
      "title": "Sr. Product Manager",
      "company": "ReflexAI",
      "location": "Remote",
      "url": "https://jobs.ashbyhq.com/reflexai/28ccd1e0-6d70-425d-9165-29e0ad939207"
    },
    {
      "n": 5,
      "title": "Principal Product Manager",
      "company": "Inovalon",
      "location": "Remote- United States",
      "url": "https://www.inovalon.com/careers/job/?gh_jid=7769110003"
    },
    {
      "n": 6,
      "title": "Senior Manager, Product Management",
      "company": "ZoomInfo",
      "location": "Remote",
      "url": "https://www.zoominfo.com/careers?gh_jid=8581902002"
    }
  ]
}